ghana.py
ghana-1.0.1.dist-info/LICENSE
ghana-1.0.1.dist-info/METADATA
ghana-1.0.1.dist-info/WHEEL
ghana-1.0.1.dist-info/top_level.txt
ghana-1.0.1.dist-info/RECORD
