Metadata-Version: 2.1
Name: ghana
Version: 1.0.1
Summary: The List Of Ghanian Country data!
Home-page: https://github.com/Victorspy-web/ghana
Author: VED
Author-email: dicksonsmart0711@gmail.com
License: UNKNOWN
Platform: UNKNOWN
Classifier: Programming Language :: Python :: 3
Classifier: License :: OSI Approved :: MIT License
Classifier: Operating System :: OS Independent
Requires-Python: >=3.4
